purpleair/__init__.py
purpleair/__version__.py
purpleair-0.0.4.dist-info/METADATA
purpleair-0.0.4.dist-info/WHEEL
purpleair-0.0.4.dist-info/top_level.txt
purpleair-0.0.4.dist-info/RECORD
