Metadata-Version: 2.1
Name: purpleair
Version: 0.0.4
Home-page: http://github.com/csm10495/purpleair
Author: csm10495
Author-email: csm10495@gmail.com
License: MIT License
Classifier: Intended Audience :: Developers
Classifier: Natural Language :: English
Classifier: Operating System :: Microsoft :: Windows
Classifier: Operating System :: POSIX :: Linux
Classifier: Operating System :: MacOS
Classifier: Programming Language :: Python
Classifier: Programming Language :: Python :: 3
Requires-Python: >=3.7
Requires-Dist: requests
Requires-Dist: cachetools
